Metadata-Version: 2.1
Name: titleweektrend
Version: 0.0.2
Summary: You can use it to get the sum of Google Trends for each word in a news or video title over the past week.
Home-page: https://github.com/xga0/titleWeekTrend
Author: Sean Gao
Author-email: seangaoxy@gmail.com
License: UNKNOWN
Platform: UNKNOWN
Classifier: Programming Language :: Python :: 3
Classifier: License :: OSI Approved :: MIT License
Classifier: Operating System :: OS Independent
Requires-Python: >=3.6
